{"cameraMode":{"drawMode":0,"name":"Shaded","section":"Shading Mode"},"sceneLighting":false,"audioPlay":false,"sceneViewState":{"showFog":true,"showMaterialUpdate":false,"showSkybox":false,"showFlares":true,"showImageEffects":true,"showParticleSystems":true},"in2DMode":false,"pivot":{"x":0.00009655952453613281,"y":0.8213902115821838,"z":0.020332425832748414},"rotation":{"x":-0.054620254784822467,"y":0.9425586462020874,"z":-0.26491332054138186,"w":-0.1960122436285019},"size":38.979888916015628,"orthographic":false}